cellmlmanip/__init__.py
cellmlmanip/_config.py
cellmlmanip/_singularity_fixes.py
cellmlmanip/main.py
cellmlmanip/model.py
cellmlmanip/parser.py
cellmlmanip/printer.py
cellmlmanip/rdf.py
cellmlmanip/units.py
cellmlmanip/version.txt
cellmlmanip/data/cellml_1_0.rnc
cellmlmanip/data/cellml_1_0.rng
cellmlmanip/data/cellml_units.txt
cellmlmanip/data/mathml2.rnc
cellmlmanip/data/mathml2.rng
cellmlmanip-0.3.6.dist-info/LICENSE
cellmlmanip-0.3.6.dist-info/METADATA
cellmlmanip-0.3.6.dist-info/WHEEL
cellmlmanip-0.3.6.dist-info/top_level.txt
cellmlmanip-0.3.6.dist-info/RECORD
