Metadata-Version: 2.1
Name: cellmlmanip
Version: 0.3.6
Summary: CellML loading and model equation manipulation
Home-page: https://github.com/ModellingWebLab/cellmlmanip
Author: Asif U Tamuri, Sarah M Keating, Maurice Hendrix, Michael Clerx, Jonathan Cooper
Author-email: j.p.cooper@ucl.ac.uk
Classifier: Programming Language :: Python :: 3
Classifier: License :: OSI Approved :: BSD License
Classifier: Operating System :: OS Independent
Requires-Python: >=3.6
License-File: LICENSE
Requires-Dist: lxml (<5,>=4.6.5)
Requires-Dist: networkx (>=2.1)
Requires-Dist: Pint (<0.20,>=0.9)
Requires-Dist: rdflib (>=4)
Requires-Dist: sympy (>=1.4)
Provides-Extra: docs
Requires-Dist: sphinx (>=2.0) ; extra == 'docs'
Provides-Extra: test
Requires-Dist: codecov ; extra == 'test'
Requires-Dist: flake8 ; extra == 'test'
Requires-Dist: isort ; extra == 'test'
Requires-Dist: pytest (>=6.0) ; extra == 'test'
Requires-Dist: pytest-cov ; extra == 'test'
